skydy/__init__.py
skydy/analysers/__init__.py
skydy/analysers/lie_bracket.py
skydy/configuration/BaseSymbols.py
skydy/configuration/Configuration.py
skydy/configuration/__init__.py
skydy/connectors/Connection.py
skydy/connectors/DOF.py
skydy/connectors/Joint.py
skydy/connectors/__init__.py
skydy/inertia/InertiaMatrix.py
skydy/inertia/MassMatrix.py
skydy/inertia/__init__.py
skydy/multibody/MultiBody.py
skydy/multibody/__init__.py
skydy/output/Arrow3D.py
skydy/output/LatexDocument.py
skydy/output/__init__.py
skydy/output/get_output_dir.py
skydy/rigidbody/Body.py
skydy/rigidbody/BodyCoordinate.py
skydy/rigidbody/BodyForce.py
skydy/rigidbody/__init__.py
skydy-0.0.3.dist-info/LICENCE
skydy-0.0.3.dist-info/METADATA
skydy-0.0.3.dist-info/WHEEL
skydy-0.0.3.dist-info/top_level.txt
skydy-0.0.3.dist-info/RECORD
