Metadata-Version: 2.1
Name: skydy
Version: 0.0.3
Summary: A package to programmatically model inter-connected mechanical systems.
Home-page: https://github.com/smkyle90/skydy
Author: Scott Kyle
Author-email: scott.m.kyle@gmail.com
License: UNKNOWN
Project-URL: Documentation, https://skydy.readthedocs.io/
Project-URL: Bug Tracker, https://github.com/smkyle90/skydy/issues
Platform: UNKNOWN
Classifier: Programming Language :: Python :: 3
Classifier: License :: OSI Approved :: MIT License
Classifier: Operating System :: OS Independent
Requires-Python: >=3.6
License-File: LICENCE
Requires-Dist: numpy
Requires-Dist: sympy
Requires-Dist: matplotlib
